{
  "entityType" : "DEVICE",
  "entity" : {
    "additionalInfo" : {
      "gateway" : false,
      "overwriteActivityTime" : false,
      "description" : ""
    },
    "customerId" : {
      "entityType" : "CUSTOMER",
      "id" : "b9784160-127e-11ef-8a9c-0bbae15aee71"
    },
    "deviceData" : {
      "configuration" : {
        "type" : "DEFAULT"
      },
      "transportConfiguration" : {
        "type" : "DEFAULT"
      }
    },
    "deviceProfileId" : {
      "entityType" : "DEVICE_PROFILE",
      "id" : "b9672a60-127e-11ef-8a9c-0bbae15aee71"
    },
    "externalId" : null,
    "firmwareId" : null,
    "id" : {
      "entityType" : "DEVICE",
      "id" : "fc871460-4d78-11ef-aac4-6f8a84baac26"
    },
    "label" : "W1 Stall-6",
    "name" : "Occupancy Sensor W1C6",
    "ownerId" : {
      "entityType" : "CUSTOMER",
      "id" : "b9784160-127e-11ef-8a9c-0bbae15aee71"
    },
    "softwareId" : null,
    "type" : "Occupancy Sensor"
  },
  "credentials" : {
    "credentialsId" : "6JhkqA5iL3egj2xGpykq",
    "credentialsType" : "ACCESS_TOKEN",
    "credentialsValue" : null
  },
  "relations" : [ {
    "additionalInfo" : null,
    "from" : {
      "entityType" : "INTEGRATION",
      "id" : "82978840-498d-11ef-aac4-6f8a84baac26"
    },
    "to" : {
      "entityType" : "DEVICE",
      "id" : "fc871460-4d78-11ef-aac4-6f8a84baac26"
    },
    "type" : "ManagedByIntegration",
    "typeGroup" : "COMMON"
  }, {
    "additionalInfo" : null,
    "from" : {
      "entityType" : "ASSET",
      "id" : "b99c1d10-127e-11ef-8a9c-0bbae15aee71"
    },
    "to" : {
      "entityType" : "DEVICE",
      "id" : "fc871460-4d78-11ef-aac4-6f8a84baac26"
    },
    "type" : "Contains",
    "typeGroup" : "COMMON"
  } ],
  "attributes" : {
    "SERVER_SCOPE" : [ {
      "booleanValue" : true,
      "doubleValue" : null,
      "jsonValue" : null,
      "key" : "active",
      "lastUpdateTs" : 1724580562886,
      "longValue" : null,
      "strValue" : null
    }, {
      "booleanValue" : null,
      "doubleValue" : null,
      "jsonValue" : null,
      "key" : "inactivityAlarmTime",
      "lastUpdateTs" : 1724580387225,
      "longValue" : 1724580387225,
      "strValue" : null
    }, {
      "booleanValue" : null,
      "doubleValue" : null,
      "jsonValue" : null,
      "key" : "lastActivityTime",
      "lastUpdateTs" : 1724581270876,
      "longValue" : 1724581269943,
      "strValue" : null
    }, {
      "booleanValue" : null,
      "doubleValue" : null,
      "jsonValue" : null,
      "key" : "state",
      "lastUpdateTs" : 1723924445014,
      "longValue" : null,
      "strValue" : "critical"
    }, {
      "booleanValue" : null,
      "doubleValue" : 0.4920017511671599,
      "jsonValue" : null,
      "key" : "xPos",
      "lastUpdateTs" : 1724145998742,
      "longValue" : null,
      "strValue" : null
    }, {
      "booleanValue" : null,
      "doubleValue" : 0.8626104123408177,
      "jsonValue" : null,
      "key" : "yPos",
      "lastUpdateTs" : 1724145998742,
      "longValue" : null,
      "strValue" : null
    } ],
    "SHARED_SCOPE" : [ ]
  }
}